MANIFEST.in
README.txt
setup.cfg
setup.py
foaftmda/__init__.py
foaftmda/command.py
foaftmda.egg-info/PKG-INFO
foaftmda.egg-info/SOURCES.txt
foaftmda.egg-info/dependency_links.txt
foaftmda.egg-info/entry_points.txt
foaftmda.egg-info/not-zip-safe
foaftmda.egg-info/requires.txt
foaftmda.egg-info/top_level.txt