Metadata-Version: 1.0
Name: foaftmda
Version: 0.1
Summary: Integration of FOAF into TMDA
Home-page: http://river.styx.org/~ww/2010/10/foaftmda/
Author: William Waites
Author-email: ww@styx.org
License: BSD
Platform: UNKNOWN
